<annotation>
	<folder/>
	<filename>frame_0710.jpg</filename>
	<path>obj//frame_0710.jpg</path>
	<source>
		<database>Unknown</database>
	</source>
	<size>
		<width>2704</width>
		<height>1520</height>
		<depth>3</depth>
	</size>
	<segmented>0</segmented>
	<object>
		<name>Pedestrian</name>
		<pose>Unspecified</pose>
		<truncated>0</truncated>
		<difficult>0</difficult>
		<bndbox>
			<xmin>653</xmin>
			<ymin>1090</ymin>
			<xmax>730</xmax>
			<ymax>1251</ymax>
		</bndbox>
	</object>
	<object>
		<name>Pedestrian</name>
		<pose>Unspecified</pose>
		<truncated>0</truncated>
		<difficult>0</difficult>
		<bndbox>
			<xmin>627</xmin>
			<ymin>966</ymin>
			<xmax>717</xmax>
			<ymax>1122</ymax>
		</bndbox>
	</object>
	<object>
		<name>Pedestrian</name>
		<pose>Unspecified</pose>
		<truncated>0</truncated>
		<difficult>0</difficult>
		<bndbox>
			<xmin>714</xmin>
			<ymin>947</ymin>
			<xmax>764</xmax>
			<ymax>1076</ymax>
		</bndbox>
	</object>
	<object>
		<name>Pedestrian</name>
		<pose>Unspecified</pose>
		<truncated>0</truncated>
		<difficult>0</difficult>
		<bndbox>
			<xmin>761</xmin>
			<ymin>904</ymin>
			<xmax>833</xmax>
			<ymax>1017</ymax>
		</bndbox>
	</object>
	<object>
		<name>Pedestrian</name>
		<pose>Unspecified</pose>
		<truncated>0</truncated>
		<difficult>0</difficult>
		<bndbox>
			<xmin>764</xmin>
			<ymin>998</ymin>
			<xmax>818</xmax>
			<ymax>1075</ymax>
		</bndbox>
	</object>
	<object>
		<name>Pedestrian</name>
		<pose>Unspecified</pose>
		<truncated>0</truncated>
		<difficult>0</difficult>
		<bndbox>
			<xmin>866</xmin>
			<ymin>1143</ymin>
			<xmax>929</xmax>
			<ymax>1278</ymax>
		</bndbox>
	</object>
	<object>
		<name>Pedestrian</name>
		<pose>Unspecified</pose>
		<truncated>0</truncated>
		<difficult>0</difficult>
		<bndbox>
			<xmin>886</xmin>
			<ymin>1029</ymin>
			<xmax>928</xmax>
			<ymax>1203</ymax>
		</bndbox>
	</object>
	<object>
		<name>Pedestrian</name>
		<pose>Unspecified</pose>
		<truncated>0</truncated>
		<difficult>0</difficult>
		<bndbox>
			<xmin>906</xmin>
			<ymin>988</ymin>
			<xmax>953</xmax>
			<ymax>1141</ymax>
		</bndbox>
	</object>
	<object>
		<name>Pedestrian</name>
		<pose>Unspecified</pose>
		<truncated>0</truncated>
		<difficult>0</difficult>
		<bndbox>
			<xmin>753</xmin>
			<ymin>1207</ymin>
			<xmax>821</xmax>
			<ymax>1369</ymax>
		</bndbox>
	</object>
	<object>
		<name>Pedestrian</name>
		<pose>Unspecified</pose>
		<truncated>0</truncated>
		<difficult>0</difficult>
		<bndbox>
			<xmin>377</xmin>
			<ymin>863</ymin>
			<xmax>437</xmax>
			<ymax>1001</ymax>
		</bndbox>
	</object>
	<object>
		<name>Pedestrian</name>
		<pose>Unspecified</pose>
		<truncated>0</truncated>
		<difficult>0</difficult>
		<bndbox>
			<xmin>355</xmin>
			<ymin>781</ymin>
			<xmax>397</xmax>
			<ymax>886</ymax>
		</bndbox>
	</object>
	<object>
		<name>Pedestrian</name>
		<pose>Unspecified</pose>
		<truncated>0</truncated>
		<difficult>0</difficult>
		<bndbox>
			<xmin>302</xmin>
			<ymin>775</ymin>
			<xmax>350</xmax>
			<ymax>886</ymax>
		</bndbox>
	</object>
	<object>
		<name>Pedestrian</name>
		<pose>Unspecified</pose>
		<truncated>0</truncated>
		<difficult>0</difficult>
		<bndbox>
			<xmin>1209</xmin>
			<ymin>521</ymin>
			<xmax>1250</xmax>
			<ymax>582</ymax>
		</bndbox>
	</object>
	<object>
		<name>Pedestrian</name>
		<pose>Unspecified</pose>
		<truncated>0</truncated>
		<difficult>0</difficult>
		<bndbox>
			<xmin>1055</xmin>
			<ymin>525</ymin>
			<xmax>1085</xmax>
			<ymax>587</ymax>
		</bndbox>
	</object>
	<object>
		<name>Pedestrian</name>
		<pose>Unspecified</pose>
		<truncated>0</truncated>
		<difficult>0</difficult>
		<bndbox>
			<xmin>1092</xmin>
			<ymin>505</ymin>
			<xmax>1111</xmax>
			<ymax>558</ymax>
		</bndbox>
	</object>
	<object>
		<name>Pedestrian</name>
		<pose>Unspecified</pose>
		<truncated>0</truncated>
		<difficult>0</difficult>
		<bndbox>
			<xmin>536</xmin>
			<ymin>519</ymin>
			<xmax>562</xmax>
			<ymax>561</ymax>
		</bndbox>
	</object>
	<object>
		<name>Pedestrian</name>
		<pose>Unspecified</pose>
		<truncated>0</truncated>
		<difficult>0</difficult>
		<bndbox>
			<xmin>579</xmin>
			<ymin>516</ymin>
			<xmax>603</xmax>
			<ymax>570</ymax>
		</bndbox>
	</object>
	<object>
		<name>Pedestrian</name>
		<pose>Unspecified</pose>
		<truncated>0</truncated>
		<difficult>0</difficult>
		<bndbox>
			<xmin>479</xmin>
			<ymin>533</ymin>
			<xmax>500</xmax>
			<ymax>583</ymax>
		</bndbox>
	</object>
	<object>
		<name>Pedestrian</name>
		<pose>Unspecified</pose>
		<truncated>0</truncated>
		<difficult>0</difficult>
		<bndbox>
			<xmin>1479</xmin>
			<ymin>562</ymin>
			<xmax>1497</xmax>
			<ymax>616</ymax>
		</bndbox>
	</object>
	<object>
		<name>Pedestrian</name>
		<pose>Unspecified</pose>
		<truncated>0</truncated>
		<difficult>0</difficult>
		<bndbox>
			<xmin>1426</xmin>
			<ymin>544</ymin>
			<xmax>1448</xmax>
			<ymax>599</ymax>
		</bndbox>
	</object>
	<object>
		<name>Pedestrian</name>
		<pose>Unspecified</pose>
		<truncated>0</truncated>
		<difficult>0</difficult>
		<bndbox>
			<xmin>1652</xmin>
			<ymin>564</ymin>
			<xmax>1680</xmax>
			<ymax>621</ymax>
		</bndbox>
	</object>
	<object>
		<name>Pedestrian</name>
		<pose>Unspecified</pose>
		<truncated>0</truncated>
		<difficult>0</difficult>
		<bndbox>
			<xmin>1688</xmin>
			<ymin>559</ymin>
			<xmax>1708</xmax>
			<ymax>618</ymax>
		</bndbox>
	</object>
	<object>
		<name>Pedestrian</name>
		<pose>Unspecified</pose>
		<truncated>0</truncated>
		<difficult>0</difficult>
		<bndbox>
			<xmin>1714</xmin>
			<ymin>608</ymin>
			<xmax>1734</xmax>
			<ymax>661</ymax>
		</bndbox>
	</object>
	<object>
		<name>Pedestrian</name>
		<pose>Unspecified</pose>
		<truncated>0</truncated>
		<difficult>0</difficult>
		<bndbox>
			<xmin>1785</xmin>
			<ymin>626</ymin>
			<xmax>1810</xmax>
			<ymax>692</ymax>
		</bndbox>
	</object>
	<object>
		<name>Pedestrian</name>
		<pose>Unspecified</pose>
		<truncated>0</truncated>
		<difficult>0</difficult>
		<bndbox>
			<xmin>2152</xmin>
			<ymin>905</ymin>
			<xmax>2203</xmax>
			<ymax>1008</ymax>
		</bndbox>
	</object>
	<object>
		<name>Pedestrian</name>
		<pose>Unspecified</pose>
		<truncated>0</truncated>
		<difficult>0</difficult>
		<bndbox>
			<xmin>2199</xmin>
			<ymin>915</ymin>
			<xmax>2246</xmax>
			<ymax>1012</ymax>
		</bndbox>
	</object>
	<object>
		<name>Pedestrian</name>
		<pose>Unspecified</pose>
		<truncated>0</truncated>
		<difficult>0</difficult>
		<bndbox>
			<xmin>2250</xmin>
			<ymin>913</ymin>
			<xmax>2295</xmax>
			<ymax>998</ymax>
		</bndbox>
	</object>
	<object>
		<name>Pedestrian</name>
		<pose>Unspecified</pose>
		<truncated>0</truncated>
		<difficult>0</difficult>
		<bndbox>
			<xmin>2088</xmin>
			<ymin>1185</ymin>
			<xmax>2186</xmax>
			<ymax>1309</ymax>
		</bndbox>
	</object>
	<object>
		<name>Pedestrian</name>
		<pose>Unspecified</pose>
		<truncated>0</truncated>
		<difficult>0</difficult>
		<bndbox>
			<xmin>2110</xmin>
			<ymin>1107</ymin>
			<xmax>2189</xmax>
			<ymax>1239</ymax>
		</bndbox>
	</object>
	<object>
		<name>Pedestrian</name>
		<pose>Unspecified</pose>
		<truncated>0</truncated>
		<difficult>0</difficult>
		<bndbox>
			<xmin>1951</xmin>
			<ymin>1048</ymin>
			<xmax>2015</xmax>
			<ymax>1168</ymax>
		</bndbox>
	</object>
	<object>
		<name>Pedestrian</name>
		<pose>Unspecified</pose>
		<truncated>0</truncated>
		<difficult>0</difficult>
		<bndbox>
			<xmin>1958</xmin>
			<ymin>1004</ymin>
			<xmax>2000</xmax>
			<ymax>1086</ymax>
		</bndbox>
	</object>
</annotation>
