<annotation>
	<folder/>
	<filename>00000116.jpg</filename>
	<path>obj//00000116.jpg</path>
	<source>
		<database>Unknown</database>
	</source>
	<size>
		<width>1024</width>
		<height>576</height>
		<depth>3</depth>
	</size>
	<segmented>0</segmented>
	<object>
		<name>Pedestrian</name>
		<pose>Unspecified</pose>
		<truncated>0</truncated>
		<difficult>0</difficult>
		<bndbox>
			<xmin>458</xmin>
			<ymin>0</ymin>
			<xmax>492</xmax>
			<ymax>23</ymax>
		</bndbox>
	</object>
	<object>
		<name>Pedestrian</name>
		<pose>Unspecified</pose>
		<truncated>0</truncated>
		<difficult>0</difficult>
		<bndbox>
			<xmin>348</xmin>
			<ymin>130</ymin>
			<xmax>388</xmax>
			<ymax>204</ymax>
		</bndbox>
	</object>
	<object>
		<name>Pedestrian</name>
		<pose>Unspecified</pose>
		<truncated>0</truncated>
		<difficult>0</difficult>
		<bndbox>
			<xmin>236</xmin>
			<ymin>569</ymin>
			<xmax>264</xmax>
			<ymax>575</ymax>
		</bndbox>
	</object>
	<object>
		<name>Pedestrian</name>
		<pose>Unspecified</pose>
		<truncated>0</truncated>
		<difficult>0</difficult>
		<bndbox>
			<xmin>761</xmin>
			<ymin>55</ymin>
			<xmax>793</xmax>
			<ymax>121</ymax>
		</bndbox>
	</object>
	<object>
		<name>Pedestrian</name>
		<pose>Unspecified</pose>
		<truncated>0</truncated>
		<difficult>0</difficult>
		<bndbox>
			<xmin>1004</xmin>
			<ymin>223</ymin>
			<xmax>1023</xmax>
			<ymax>258</ymax>
		</bndbox>
	</object>
	<object>
		<name>Pedestrian</name>
		<pose>Unspecified</pose>
		<truncated>0</truncated>
		<difficult>0</difficult>
		<bndbox>
			<xmin>674</xmin>
			<ymin>54</ymin>
			<xmax>714</xmax>
			<ymax>123</ymax>
		</bndbox>
	</object>
</annotation>
