<annotation>
	<folder/>
	<filename>frame_0756.jpg</filename>
	<path>obj//frame_0756.jpg</path>
	<source>
		<database>Unknown</database>
	</source>
	<size>
		<width>2704</width>
		<height>1520</height>
		<depth>3</depth>
	</size>
	<segmented>0</segmented>
	<object>
		<name>Pedestrian</name>
		<pose>Unspecified</pose>
		<truncated>0</truncated>
		<difficult>0</difficult>
		<bndbox>
			<xmin>508</xmin>
			<ymin>1184</ymin>
			<xmax>581</xmax>
			<ymax>1326</ymax>
		</bndbox>
	</object>
	<object>
		<name>Pedestrian</name>
		<pose>Unspecified</pose>
		<truncated>0</truncated>
		<difficult>0</difficult>
		<bndbox>
			<xmin>496</xmin>
			<ymin>1078</ymin>
			<xmax>568</xmax>
			<ymax>1216</ymax>
		</bndbox>
	</object>
	<object>
		<name>Pedestrian</name>
		<pose>Unspecified</pose>
		<truncated>0</truncated>
		<difficult>0</difficult>
		<bndbox>
			<xmin>533</xmin>
			<ymin>974</ymin>
			<xmax>600</xmax>
			<ymax>1138</ymax>
		</bndbox>
	</object>
	<object>
		<name>Pedestrian</name>
		<pose>Unspecified</pose>
		<truncated>0</truncated>
		<difficult>0</difficult>
		<bndbox>
			<xmin>663</xmin>
			<ymin>1091</ymin>
			<xmax>737</xmax>
			<ymax>1272</ymax>
		</bndbox>
	</object>
	<object>
		<name>Pedestrian</name>
		<pose>Unspecified</pose>
		<truncated>0</truncated>
		<difficult>0</difficult>
		<bndbox>
			<xmin>904</xmin>
			<ymin>1166</ymin>
			<xmax>973</xmax>
			<ymax>1307</ymax>
		</bndbox>
	</object>
	<object>
		<name>Pedestrian</name>
		<pose>Unspecified</pose>
		<truncated>0</truncated>
		<difficult>0</difficult>
		<bndbox>
			<xmin>862</xmin>
			<ymin>1083</ymin>
			<xmax>915</xmax>
			<ymax>1247</ymax>
		</bndbox>
	</object>
	<object>
		<name>Pedestrian</name>
		<pose>Unspecified</pose>
		<truncated>0</truncated>
		<difficult>0</difficult>
		<bndbox>
			<xmin>893</xmin>
			<ymin>1026</ymin>
			<xmax>959</xmax>
			<ymax>1182</ymax>
		</bndbox>
	</object>
	<object>
		<name>Pedestrian</name>
		<pose>Unspecified</pose>
		<truncated>0</truncated>
		<difficult>0</difficult>
		<bndbox>
			<xmin>758</xmin>
			<ymin>927</ymin>
			<xmax>812</xmax>
			<ymax>1065</ymax>
		</bndbox>
	</object>
	<object>
		<name>Pedestrian</name>
		<pose>Unspecified</pose>
		<truncated>0</truncated>
		<difficult>0</difficult>
		<bndbox>
			<xmin>840</xmin>
			<ymin>949</ymin>
			<xmax>894</xmax>
			<ymax>1054</ymax>
		</bndbox>
	</object>
	<object>
		<name>Pedestrian</name>
		<pose>Unspecified</pose>
		<truncated>0</truncated>
		<difficult>0</difficult>
		<bndbox>
			<xmin>409</xmin>
			<ymin>923</ymin>
			<xmax>487</xmax>
			<ymax>1063</ymax>
		</bndbox>
	</object>
	<object>
		<name>Pedestrian</name>
		<pose>Unspecified</pose>
		<truncated>0</truncated>
		<difficult>0</difficult>
		<bndbox>
			<xmin>364</xmin>
			<ymin>829</ymin>
			<xmax>429</xmax>
			<ymax>947</ymax>
		</bndbox>
	</object>
	<object>
		<name>Pedestrian</name>
		<pose>Unspecified</pose>
		<truncated>0</truncated>
		<difficult>0</difficult>
		<bndbox>
			<xmin>291</xmin>
			<ymin>842</ymin>
			<xmax>344</xmax>
			<ymax>977</ymax>
		</bndbox>
	</object>
	<object>
		<name>Pedestrian</name>
		<pose>Unspecified</pose>
		<truncated>0</truncated>
		<difficult>0</difficult>
		<bndbox>
			<xmin>314</xmin>
			<ymin>827</ymin>
			<xmax>356</xmax>
			<ymax>949</ymax>
		</bndbox>
	</object>
	<object>
		<name>Pedestrian</name>
		<pose>Unspecified</pose>
		<truncated>0</truncated>
		<difficult>0</difficult>
		<bndbox>
			<xmin>256</xmin>
			<ymin>756</ymin>
			<xmax>303</xmax>
			<ymax>860</ymax>
		</bndbox>
	</object>
	<object>
		<name>Pedestrian</name>
		<pose>Unspecified</pose>
		<truncated>0</truncated>
		<difficult>0</difficult>
		<bndbox>
			<xmin>375</xmin>
			<ymin>683</ymin>
			<xmax>419</xmax>
			<ymax>769</ymax>
		</bndbox>
	</object>
	<object>
		<name>Pedestrian</name>
		<pose>Unspecified</pose>
		<truncated>0</truncated>
		<difficult>0</difficult>
		<bndbox>
			<xmin>502</xmin>
			<ymin>766</ymin>
			<xmax>538</xmax>
			<ymax>876</ymax>
		</bndbox>
	</object>
	<object>
		<name>Pedestrian</name>
		<pose>Unspecified</pose>
		<truncated>0</truncated>
		<difficult>0</difficult>
		<bndbox>
			<xmin>577</xmin>
			<ymin>656</ymin>
			<xmax>621</xmax>
			<ymax>758</ymax>
		</bndbox>
	</object>
	<object>
		<name>Pedestrian</name>
		<pose>Unspecified</pose>
		<truncated>0</truncated>
		<difficult>0</difficult>
		<bndbox>
			<xmin>320</xmin>
			<ymin>766</ymin>
			<xmax>350</xmax>
			<ymax>839</ymax>
		</bndbox>
	</object>
	<object>
		<name>Pedestrian</name>
		<pose>Unspecified</pose>
		<truncated>0</truncated>
		<difficult>0</difficult>
		<bndbox>
			<xmin>362</xmin>
			<ymin>758</ymin>
			<xmax>410</xmax>
			<ymax>839</ymax>
		</bndbox>
	</object>
	<object>
		<name>Pedestrian</name>
		<pose>Unspecified</pose>
		<truncated>0</truncated>
		<difficult>0</difficult>
		<bndbox>
			<xmin>807</xmin>
			<ymin>551</ymin>
			<xmax>841</xmax>
			<ymax>613</ymax>
		</bndbox>
	</object>
	<object>
		<name>Pedestrian</name>
		<pose>Unspecified</pose>
		<truncated>0</truncated>
		<difficult>0</difficult>
		<bndbox>
			<xmin>751</xmin>
			<ymin>553</ymin>
			<xmax>770</xmax>
			<ymax>616</ymax>
		</bndbox>
	</object>
	<object>
		<name>Pedestrian</name>
		<pose>Unspecified</pose>
		<truncated>0</truncated>
		<difficult>0</difficult>
		<bndbox>
			<xmin>1058</xmin>
			<ymin>526</ymin>
			<xmax>1084</xmax>
			<ymax>578</ymax>
		</bndbox>
	</object>
	<object>
		<name>Pedestrian</name>
		<pose>Unspecified</pose>
		<truncated>0</truncated>
		<difficult>0</difficult>
		<bndbox>
			<xmin>1105</xmin>
			<ymin>510</ymin>
			<xmax>1119</xmax>
			<ymax>568</ymax>
		</bndbox>
	</object>
	<object>
		<name>Pedestrian</name>
		<pose>Unspecified</pose>
		<truncated>0</truncated>
		<difficult>0</difficult>
		<bndbox>
			<xmin>1233</xmin>
			<ymin>537</ymin>
			<xmax>1262</xmax>
			<ymax>592</ymax>
		</bndbox>
	</object>
	<object>
		<name>Pedestrian</name>
		<pose>Unspecified</pose>
		<truncated>0</truncated>
		<difficult>0</difficult>
		<bndbox>
			<xmin>1633</xmin>
			<ymin>553</ymin>
			<xmax>1649</xmax>
			<ymax>610</ymax>
		</bndbox>
	</object>
	<object>
		<name>Pedestrian</name>
		<pose>Unspecified</pose>
		<truncated>0</truncated>
		<difficult>0</difficult>
		<bndbox>
			<xmin>1781</xmin>
			<ymin>640</ymin>
			<xmax>1817</xmax>
			<ymax>711</ymax>
		</bndbox>
	</object>
	<object>
		<name>Pedestrian</name>
		<pose>Unspecified</pose>
		<truncated>0</truncated>
		<difficult>0</difficult>
		<bndbox>
			<xmin>1824</xmin>
			<ymin>633</ymin>
			<xmax>1852</xmax>
			<ymax>703</ymax>
		</bndbox>
	</object>
	<object>
		<name>Pedestrian</name>
		<pose>Unspecified</pose>
		<truncated>0</truncated>
		<difficult>0</difficult>
		<bndbox>
			<xmin>2046</xmin>
			<ymin>789</ymin>
			<xmax>2082</xmax>
			<ymax>876</ymax>
		</bndbox>
	</object>
	<object>
		<name>Pedestrian</name>
		<pose>Unspecified</pose>
		<truncated>0</truncated>
		<difficult>0</difficult>
		<bndbox>
			<xmin>2016</xmin>
			<ymin>1128</ymin>
			<xmax>2079</xmax>
			<ymax>1266</ymax>
		</bndbox>
	</object>
	<object>
		<name>Pedestrian</name>
		<pose>Unspecified</pose>
		<truncated>0</truncated>
		<difficult>0</difficult>
		<bndbox>
			<xmin>2005</xmin>
			<ymin>1031</ymin>
			<xmax>2067</xmax>
			<ymax>1176</ymax>
		</bndbox>
	</object>
	<object>
		<name>Pedestrian</name>
		<pose>Unspecified</pose>
		<truncated>0</truncated>
		<difficult>0</difficult>
		<bndbox>
			<xmin>2105</xmin>
			<ymin>1042</ymin>
			<xmax>2178</xmax>
			<ymax>1186</ymax>
		</bndbox>
	</object>
	<object>
		<name>Pedestrian</name>
		<pose>Unspecified</pose>
		<truncated>0</truncated>
		<difficult>0</difficult>
		<bndbox>
			<xmin>2097</xmin>
			<ymin>1185</ymin>
			<xmax>2187</xmax>
			<ymax>1310</ymax>
		</bndbox>
	</object>
	<object>
		<name>Pedestrian</name>
		<pose>Unspecified</pose>
		<truncated>0</truncated>
		<difficult>0</difficult>
		<bndbox>
			<xmin>2197</xmin>
			<ymin>1218</ymin>
			<xmax>2289</xmax>
			<ymax>1353</ymax>
		</bndbox>
	</object>
	<object>
		<name>Pedestrian</name>
		<pose>Unspecified</pose>
		<truncated>0</truncated>
		<difficult>0</difficult>
		<bndbox>
			<xmin>2099</xmin>
			<ymin>958</ymin>
			<xmax>2175</xmax>
			<ymax>1095</ymax>
		</bndbox>
	</object>
	<object>
		<name>Pedestrian</name>
		<pose>Unspecified</pose>
		<truncated>0</truncated>
		<difficult>0</difficult>
		<bndbox>
			<xmin>2299</xmin>
			<ymin>923</ymin>
			<xmax>2358</xmax>
			<ymax>1033</ymax>
		</bndbox>
	</object>
	<object>
		<name>Pedestrian</name>
		<pose>Unspecified</pose>
		<truncated>0</truncated>
		<difficult>0</difficult>
		<bndbox>
			<xmin>2249</xmin>
			<ymin>914</ymin>
			<xmax>2293</xmax>
			<ymax>1014</ymax>
		</bndbox>
	</object>
	<object>
		<name>Pedestrian</name>
		<pose>Unspecified</pose>
		<truncated>0</truncated>
		<difficult>0</difficult>
		<bndbox>
			<xmin>2201</xmin>
			<ymin>901</ymin>
			<xmax>2242</xmax>
			<ymax>1000</ymax>
		</bndbox>
	</object>
	<object>
		<name>Pedestrian</name>
		<pose>Unspecified</pose>
		<truncated>0</truncated>
		<difficult>0</difficult>
		<bndbox>
			<xmin>2178</xmin>
			<ymin>902</ymin>
			<xmax>2210</xmax>
			<ymax>1001</ymax>
		</bndbox>
	</object>
	<object>
		<name>Pedestrian</name>
		<pose>Unspecified</pose>
		<truncated>0</truncated>
		<difficult>0</difficult>
		<bndbox>
			<xmin>2144</xmin>
			<ymin>905</ymin>
			<xmax>2174</xmax>
			<ymax>981</ymax>
		</bndbox>
	</object>
</annotation>
